beancount_ing/__init__.py
beancount_ing/ec.py
beancount_ing-1.1.0.dist-info/LICENSE.txt
beancount_ing-1.1.0.dist-info/METADATA
beancount_ing-1.1.0.dist-info/WHEEL
beancount_ing-1.1.0.dist-info/RECORD
