Metadata-Version: 2.3
Name: beancount-ing
Version: 1.1.0
Summary: Beancount Importer for ING (DE) CSV exports
Home-page: https://github.com/siddhantgoel/beancount-ing
License: MIT
Keywords: banking,beancount,cli-accounting,finance
Author: Siddhant Goel
Author-email: me@sgoel.dev
Requires-Python: >=3.9,<4.0
Classifier: Development Status :: 4 - Beta
Classifier: Environment :: Plugins
Classifier: Intended Audience :: End Users/Desktop
Classifier: Intended Audience :: Financial and Insurance Industry
Classifier: License :: OSI Approved :: MIT License
Classifier: Programming Language :: Python :: 3
Classifier: Programming Language :: Python :: 3.9
Classifier: Programming Language :: Python :: 3.10
Classifier: Programming Language :: Python :: 3.11
Classifier: Programming Language :: Python :: 3.12
Classifier: Programming Language :: Python :: 3.13
Classifier: Programming Language :: Python :: 3 :: Only
Requires-Dist: beancount (>=2.3.5)
Requires-Dist: beangulp (>=0.1.1,<0.3.0)
Project-URL: Repository, https://github.com/siddhantgoel/beancount-ing
